README.rst
setup.cfg
setup.py
lambdAWS/S3.py
lambdAWS/SNS.py
lambdAWS/__init__.py
lambdAWS/event.py
lambdAWS/record.py
lambdAWS/test_event.py
lambdAWS/test_s3.py
lambdAWS.egg-info/PKG-INFO
lambdAWS.egg-info/SOURCES.txt
lambdAWS.egg-info/dependency_links.txt
lambdAWS.egg-info/top_level.txt