Metadata-Version: 1.1
Name: lambdAWS
Version: 0.1.8
Summary: lambda에서 각종 AWS서비스를 사용하기 위한 래핑모듈
Home-page: https://bitbucket.org/indjdev/lambdaws
Author: wesky93
Author-email: wesky93@gmail.com
License: MIT License
Keywords: aws,lambda,s3,sns,dynamodb
Platform: UNKNOWN
Classifier: Development Status :: 3 - Alpha
Classifier: Intended Audience :: Developers
Classifier: Programming Language :: Python
Classifier: Programming Language :: Python :: 2
Classifier: Programming Language :: Python :: 3
Classifier: License :: OSI Approved :: MIT License
